pySnowRadar/__init__.py
pySnowRadar/atm.py
pySnowRadar/geofunc.py
pySnowRadar/matfunc.py
pySnowRadar/processing.py
pySnowRadar/qc.py
pySnowRadar/snowradar.py
pySnowRadar/timefunc.py
pySnowRadar/algorithms/GSFC.py
pySnowRadar/algorithms/Peakiness.py
pySnowRadar/algorithms/Wavelet.py
pySnowRadar/algorithms/__init__.py
pySnowRadar/data/natearth/ne_10m_admin_0_countries_northamerica.zip
pySnowRadar-1.1.1.dist-info/LICENSE
pySnowRadar-1.1.1.dist-info/METADATA
pySnowRadar-1.1.1.dist-info/WHEEL
pySnowRadar-1.1.1.dist-info/top_level.txt
pySnowRadar-1.1.1.dist-info/RECORD
