Metadata-Version: 2.1
Name: pySnowRadar
Version: 1.1.1
Summary: A Python3 package to process data from CRESIS SnowRadar systems
Home-page: https://github.com/kingjml/pySnowRadar
Author: Climate Research Division
Author-email: 
License: MIT
Project-URL: Source, https://github.com/kingjml/pySnowRadar
Project-URL: Tracker, https://github.com/kingjml/pySnowRadar/issues
Keywords: snowradar
Platform: UNKNOWN
Classifier: Development Status :: 5 - Production/Stable
Classifier: Topic :: Scientific/Engineering
Classifier: Intended Audience :: Science/Research
Classifier: Intended Audience :: Education
Classifier: License :: OSI Approved :: MIT License
Classifier: Operating System :: Microsoft :: Windows
Classifier: Operating System :: POSIX :: Linux
Classifier: Programming Language :: Python :: 3 :: Only
Requires-Python: >=3,<3.8
Requires-Dist: gdal (>=2.3.3)
Requires-Dist: h5py (>=2.9)
Requires-Dist: matplotlib (>=3.1)
Requires-Dist: numpy (>=1.16)
Requires-Dist: pywavelets (>=1)
Requires-Dist: shapely (>=1.6.4)
Requires-Dist: scipy (>=1.2.1)
Requires-Dist: pandas (>=0.24.2)
Requires-Dist: geopandas (>=0.4.1)
Requires-Dist: pyproj (>=1.9.6)
Provides-Extra: notebooks
Requires-Dist: jupyter ; extra == 'notebooks'
Provides-Extra: test
Requires-Dist: pytest ; extra == 'test'
Requires-Dist: coverage ; extra == 'test'
